{
  "slug": "arwyn-frey",
  "name": "Arwyn Frey",
  "type": "character.human",
  "node_path": "graph/nodes/characters/arwyn-frey.node.md",
  "generated_at": "2026-06-28T04:58:24.304987+00:00",
  "stats": {
    "appearances_total": 2,
    "chapters_pov": 0,
    "chapters_mentioned_in": 1,
    "out_edge_count": 5,
    "in_edge_count": 0
  },
  "chapters": {
    "pov": [],
    "mentioned_in": [
      {
        "chapter_id": "asos-catelyn-06",
        "book": "asos",
        "pov_character_slug": "catelyn-stark",
        "mention_count": 2,
        "sections": [
          "Character Appearances",
          "Characters Present"
        ],
        "resolved_via": "direct"
      }
    ]
  }
}